setup.py
nuvem_de_som/__init__.py
nuvem_de_som.egg-info/PKG-INFO
nuvem_de_som.egg-info/SOURCES.txt
nuvem_de_som.egg-info/dependency_links.txt
nuvem_de_som.egg-info/requires.txt
nuvem_de_som.egg-info/top_level.txt