Metadata-Version: 2.1
Name: nuvem-de-som
Version: 0.0.1a1
Summary: search soundcloud
Home-page: https://github.com/OpenJarbas/nuvem_de_som
Author: JarbasAi
License: UNKNOWN
Platform: UNKNOWN
